{
  "generatedAt": "2026-07-06T06:33:12.541Z",
  "source": {
    "repo": "armync/ArminC-CS2-Cvars",
    "path": "cvars/cvarlist.md",
    "ref": "main",
    "license": "CC0-1.0",
    "url": "https://github.com/armync/ArminC-CS2-Cvars/blob/main/cvars/cvarlist.md",
    "rawSha256": "2015DBAB6BAA87C1EA449B04F792D90C01877C757B1DB4C508E1DE852630F12D",
    "rawLines": 5084,
    "rawSize": 453929
  },
  "total": 5084,
  "duplicateCount": 0,
  "supplementalCount": 3,
  "missingDescriptionCount": 92,
  "missingReliableZhCount": 3642,
  "categories": {
    "服务器": 543,
    "未分类": 2914,
    "输入/绑定": 46,
    "启动项": 14,
    "开发/调试": 402,
    "声音": 390,
    "对局规则": 383,
    "Bot 与训练": 115,
    "画面/HUD/准星": 56,
    "常用/精选": 10,
    "地图/工坊": 124,
    "网络/性能": 55,
    "Demo/GOTV": 32
  },
  "riskLevels": {
    "普通": 3395,
    "启动项": 14,
    "开发/隐藏": 251,
    "谨慎": 1424
  }
}
